outscraper/__init__.py
outscraper/businesses.py
outscraper/client.py
outscraper/transport.py
outscraper/utils.py
outscraper-6.0.1.dist-info/licenses/LICENSE
outscraper-6.0.1.dist-info/METADATA
outscraper-6.0.1.dist-info/WHEEL
outscraper-6.0.1.dist-info/top_level.txt
outscraper-6.0.1.dist-info/RECORD
