Metadata-Version: 2.4
Name: outscraper
Version: 6.0.1
Summary: Python bindings for the Outscraper API
Home-page: https://github.com/outscraper/outscraper-python
Author: Outscraper
Author-email: support@outscraper.com
License: MIT
Keywords: outscraper webscraper extractor google api maps search json scrape parser reviews google play amazon
Classifier: Programming Language :: Python
Classifier: License :: OSI Approved :: MIT License
Classifier: Operating System :: OS Independent
Classifier: Intended Audience :: Developers
Classifier: Topic :: Utilities
License-File: LICENSE
Requires-Dist: requests
Dynamic: author
Dynamic: author-email
Dynamic: classifier
Dynamic: description
Dynamic: description-content-type
Dynamic: home-page
Dynamic: keywords
Dynamic: license
Dynamic: license-file
Dynamic: requires-dist
Dynamic: summary
